{
  "type": "скарга",
  "id": "skarga",
  "title": "Скарга на неправомірні дії командира",
  "fields": [
    {
      "id": "rank",
      "label": "Звання",
      "type": "select",
      "options": ["солдат", "старший солдат", "молодший сержант", "сержант", "старший сержант", "лейтенант", "старший лейтенант", "капітан", "майор"],
      "required": true
    },
    {
      "id": "commander_rank",
      "label": "Звання командира (на кого скарга)",
      "type": "text",
      "placeholder": "наприклад: майор Іваненко І.І.",
      "required": true
    },
    {
      "id": "violation",
      "label": "Суть порушення",
      "type": "text",
      "placeholder": "наприклад: незаконне позбавлення відпустки",
      "required": true
    },
    {
      "id": "date",
      "label": "Дата порушення",
      "type": "text",
      "placeholder": "наприклад: 15.01.2025",
      "required": true
    }
  ],
  "template_text": "Начальнику вищого органу військового управління\n\n{rank} [ПІБ],\nвійськова частина [НОМЕР В/Ч]\n\nСКАРГА\n\n{date} командир {commander_rank} вчинив щодо мене неправомірні дії, а саме: {violation}.\n\nДані дії порушують мої права як військовослужбовця, гарантовані чинним законодавством України.\n\nПрошу провести перевірку та вжити заходів для усунення допущених порушень.\n\n«___» ____________ 20__ року\n\n[ПІДПИС]",
  "note": "ПІБ, номер частини та підпис додаєте самостійно у роздрукований документ"
}
